secxbrl/__init__.py
secxbrl/extracted_xbrl.py
secxbrl/inline_xbrl.py
secxbrl/xbrl.py
secxbrl-0.1.3.dist-info/LICENSE
secxbrl-0.1.3.dist-info/METADATA
secxbrl-0.1.3.dist-info/WHEEL
secxbrl-0.1.3.dist-info/top_level.txt
secxbrl-0.1.3.dist-info/RECORD
