Metadata-Version: 2.1
Name: secxbrl
Version: 0.1.3
Summary: A package to parse SEC XBRL
License: MIT
License-File: LICENSE
Requires-Dist: selectolax
Requires-Dist: lxml
